cima/goes/__init__.py
cima/goes/data/__init__.py
cima/goes/data/_data.py
cima/goes/data/_palettes.py
cima/goes/data/smn_topes.cpt
cima/goes/img/__init__.py
cima/goes/img/_images.py
cima/goes/img/_palettes.py
cima/goes/img/smn_topes.cpt
cima/goes/projects/__init__.py
cima/goes/projects/_project.py
cima/goes/projects/OTs/__init__.py
cima/goes/projects/OTs/_save_images.py
cima/goes/projects/OTs/_tiles.py
cima/goes/projects/OTs/generate_areas.py
cima/goes/projects/OTs/save_images.py
cima/goes/storage/__init__.py
cima/goes/storage/_async_ftp.py
cima/goes/storage/_async_nfs.py
cima/goes/storage/_blobs.py
cima/goes/storage/_factories.py
cima/goes/storage/_file_systems.py
cima/goes/storage/_ftp.py
cima/goes/storage/_gcs.py
cima/goes/storage/_goes_data.py
cima/goes/storage/_http.py
cima/goes/storage/_nfs.py
cima/goes/tasks/__init__.py
cima/goes/tasks/_concurrent.py
cima/goes/tiles/__init__.py
cima/goes/tiles/_dataset_region.py
cima/goes/tiles/_tiles.py
cima/goes/utils/__init__.py
cima/goes/utils/_file_names.py
cima/goes/utils/_process_info.py
cima/goes/utils/_timeit.py
cima/goes/utils/load_cpt.py
cima.goes-1.1b92.data/data/LICENSE
cima.goes-1.1b92.dist-info/LICENSE
cima.goes-1.1b92.dist-info/METADATA
cima.goes-1.1b92.dist-info/WHEEL
cima.goes-1.1b92.dist-info/top_level.txt
cima.goes-1.1b92.dist-info/RECORD
